antvis/__init__.py
antvis/client/__init__.py
antvis/client/dashboard.py
antvis/client/httprpc.py
antvis/client/job.py
antvis/client/mlogger/__init__.py
antvis/client/mlogger/container.py
antvis/client/mlogger/variable.py
antvis/client/mlogger/complex/__init__.py
antvis/client/mlogger/file/__init__.py
antvis/client/mlogger/metric/__init__.py
antvis/client/mlogger/metric/base.py
antvis/client/mlogger/monitor/__init__.py
antvis/client/mlogger/tensorflow/__init__.py
antvis/client/mlogger/torch/__init__.py
antvis/client/style/__init__.py
antvis/client/style/tensorboard.py
antvis/client/style/visdom.py
antvis/utils/__init__.py
antvis/utils/encode.py
antvis/utils/utils.py
test/__init__.py
test/main.py
test/main2.py
test/main3.py
antvis-0.1.19.dist-info/METADATA
antvis-0.1.19.dist-info/WHEEL
antvis-0.1.19.dist-info/top_level.txt
antvis-0.1.19.dist-info/RECORD
