Metadata-Version: 2.1
Name: antvis
Version: 0.1.19
Summary: machine learning manage client
Home-page: http://www.mltalker.com
Author: jian
Author-email: jian@mltalker.com
